LICENSE
MANIFEST.in
README.md
requirements.txt
setup.py
doc/bitblasting.dot
doc/doc.md
doc/fol_to_bdd_details.dot
doc/ltl_to_bdd.dot
examples/README.md
examples/bdd_howto.py
examples/choosing_type_hints.py
examples/gr1_synthesis_intro.py
examples/inverter.py
examples/minimal_formula_from_bdd.py
examples/moore_moore.py
examples/reachability_solver.py
examples/symbolic.py
examples/while_plus_half.py
omega/__init__.py
omega/_version.py
omega/automata.py
omega/gr1.py
omega/steps.py
omega.egg-info/PKG-INFO
omega.egg-info/SOURCES.txt
omega.egg-info/dependency_links.txt
omega.egg-info/requires.txt
omega.egg-info/top_level.txt
omega/games/__init__.py
omega/games/enumeration.py
omega/games/gr1.py
omega/logic/__init__.py
omega/logic/ast.py
omega/logic/bitvector.py
omega/logic/lexyacc.py
omega/logic/ltl_parsetab.py
omega/logic/past.py
omega/logic/syntax.py
omega/logic/transformation.py
omega/symbolic/__init__.py
omega/symbolic/_type_hints.py
omega/symbolic/bdd.py
omega/symbolic/bdd_iterative.py
omega/symbolic/codegen.py
omega/symbolic/cover.py
omega/symbolic/cover_enum.py
omega/symbolic/enumeration.py
omega/symbolic/fixpoint.py
omega/symbolic/fol.py
omega/symbolic/functions.py
omega/symbolic/logicizer.py
omega/symbolic/orthotopes.py
omega/symbolic/prime.py
omega/symbolic/symbolic.py
omega/symbolic/temporal.py
spec/OpenSystems.tla
spec/Realizability.tla
spec/mincover/CyclicCore.tla
spec/mincover/FiniteSetFacts.tla
spec/mincover/Lattices.tla
spec/mincover/MinCover.tla
spec/mincover/Optimization.tla
spec/mincover/Orthotopes.tla
spec/mincover/README
spec/mincover/StrongReduction.tla
tests/bitvector_test.py
tests/codegen_test.py
tests/cover_enum_test.py
tests/cover_test.py
tests/expr_cache_test.py
tests/fixpoint_test.py
tests/fol_test.py
tests/games_enumeration_test.py
tests/games_test.py
tests/gr1_test.py
tests/lexyacc_test.py
tests/logic_test.py
tests/steps_test.py
tests/symbolic_enumeration_test.py
tests/symbolic_temporal_test.py
tests/symbolic_test.py