Metadata-Version: 2.1
Name: omega
Version: 0.4.0
Summary: Symbolic algorithms for solving games of infinite duration.
Home-page: https://github.com/tulip-control/omega
Author: Caltech Control and Dynamical Systems
Author-email: tulip@tulip-control.org
License: BSD
Project-URL: Bug Tracker, https://github.com/tulip-control/omega/issues
Project-URL: Documentation, https://github.com/tulip-control/omega/blob/main/doc/doc.md
Project-URL: Source Code, https://github.com/tulip-control/omega
Keywords: first-order,propositional,logic,quantifier,forall,exists,fixpoint,mu-calculus,formula,flatten,bitblaster,bitvector,arithmetic,binary decision diagram,symbolic,games,specification,system,assume,guarantee,satisfiability,enumeration,state machine,transition system,automaton,automata,streett,rabin,temporal logic,temporal tester,gr1,generalized reactivity
Classifier: Development Status :: 2 - Pre-Alpha
Classifier: Intended Audience :: Science/Research
Classifier: License :: OSI Approved :: BSD License
Classifier: Operating System :: OS Independent
Classifier: Programming Language :: Python
Classifier: Programming Language :: Python :: 3 :: Only
Classifier: Topic :: Scientific/Engineering
Requires-Python: >=3.11
License-File: LICENSE
Requires-Dist: astutils>=0.0.5
Requires-Dist: dd>=0.6.0
Requires-Dist: natsort>=3.5.3
Requires-Dist: networkx>=2.0
Requires-Dist: ply<=3.10,>=3.6
Requires-Dist: pydot>=1.2.2
